{
  "existing_annotations": [],
  "missing_annotations": [
    {
      "suggested_text": "効果には個人差があります",
      "reason": "動画内で「いい女なろう」という表現があり、美容・自己啓発に関連する効果を想起させる可能性があるため、効果には個人差がある旨を明記する必要がある。",
      "severity": "推奨",
      "suggested_timecode": "00:48-00:57",
      "legal_basis": "景品表示法、薬機法（医薬品、医療機器等の品質、有効性及び安全性の確保等に関する法律）に抵触する可能性を避けるため"
    },
    {
      "suggested_text": "使用している商品はインテグレートの化粧品です",
      "reason": "動画内で商品が明確に示されていないため、視聴者に対して使用されている商品ブランドを明確に伝える必要がある。特に終盤にインテグレートの商品名が出ているので、それを強調する意味でも明記すべき。",
      "severity": "推奨",
      "suggested_timecode": "00:58-01:00",
      "legal_basis": "特になし"
    },
    {
      "suggested_text": "出演者はモデルです",
      "reason": "動画に登場する人物の美しさが、商品の効果によるものと誤解されることを避けるため。",
      "severity": "任意",
      "suggested_timecode": "00:00-00:01",
      "legal_basis": "特になし"
    }
  ]
}