{
  "summary": "この動画は、インテグレートのコマーシャル映像で、25歳を迎えた女性たちが年齢と可愛さについての葛藤を描き、新しい自分を見つけるストーリーです。",
  "segments": [
    {
      "label": "誕生日パーティーのシーン",
      "description": "25歳の誕生日を祝うシーンで、主人公が年齢に対する複雑な感情を抱いている様子を描写しています。",
      "shots": [
        {
          "timecode": "0:03〜0:09",
          "description": "誕生日ケーキのアップ、友人に祝われる主人公、25歳に対する複雑な感情が会話を通して描写される。"
        },
        {
          "timecode": "0:13〜0:15",
          "description": "友人との会話から、25歳になった主人公の心境が語られる。"
        }
      ]
    },
    {
      "label": "年齢と外見への葛藤",
      "description": "主人公が自身の年齢と外見に対する不安や葛藤を抱え、新しい自分になることを決意する様子を描いています。",
      "shots": [
        {
          "timecode": "0:20〜0:27",
          "description": "友人との会話から、年齢を重ねることへの焦りや不安が語られる。"
        },
        {
          "timecode": "0:47〜0:51",
          "description": "主人公が新しい自分になる決意をする。"
        }
      ]
    },
    {
      "label": "新しい自分への変化",
      "description": "新しいメイクを通して、主人公が前向きに変化していく様子を描写しています。",
      "shots": [
        {
          "timecode": "0:52〜0:55",
          "description": "赤い背景で女性がメイクをするシーン。"
        }
      ]
    },
    {
      "label": "新しい未来への希望",
      "description": "新しい自分に生まれ変わった主人公たちが、未来に向かって走り出す姿を描き、希望に満ちたエンディングを迎えます。",
      "shots": [
        {
          "timecode": "0:56〜1:03",
          "description": "女性たちが街を駆け抜け、未来への希望を抱くシーン。"
        }
      ]
    }
  ]
}